standardiser/SDF.py
standardiser/__init__.py
standardiser/break_bonds.py
standardiser/make_logger.py
standardiser/neutralise.py
standardiser/rules.py
standardiser/rules_demo.py
standardiser/standardise.py
standardiser/unsalt.py
standardiser/utils.py
standardiser/bin/__init__.py
standardiser/bin/ipynb_to_html.sh
standardiser/bin/rules_applied.py
standardiser/bin/standardise_mols.py
standardiser/data/really_salts.tsv
standardiser/data/rules_base.dat
standardiser/data/rules_specific.dat
standardiser/data/rules_tautomerism_and_aromaticity.dat
standardiser/data/rules_to_be_used_with_caution.dat
standardiser/data/salts.tsv
standardiser/docs/00_Introduction.ipynb
standardiser/docs/01_break_bonds.ipynb
standardiser/docs/02_neutralise.ipynb
standardiser/docs/03_rules.ipynb
standardiser/docs/04_unsalt.ipynb
standardiser/docs/05_standardise.ipynb
standardiser/docs/06_alternative.ipynb
standardiser/docs/99_issue_01.ipynb
standardiser/docs/Charge-separated_systems.ipynb
standardiser/docs/Conjugated_cations_and_charge_neutralisation.ipynb
standardiser/docs/Hydroxy_pyridine_within_ring.ipynb
standardiser/docs/Keto-enol_tautomerism.ipynb
standardiser/docs/Miscellaeny.ipynb
standardiser/docs/Multiple_possible_tautomers.ipynb
standardiser/docs/Neutralisation_strategy.ipynb
standardiser/docs/Rule_application_strategy.ipynb
standardiser/docs/Tautomerism_and_aromaticity.ipynb
standardiser/docs/notebook_setup.py
standardiser/docs/standardiser.pdf
standardiser/docs/standardiser.pptx
chemo_standardizer-0.1.7.dist-info/LICENSE
chemo_standardizer-0.1.7.dist-info/METADATA
chemo_standardizer-0.1.7.dist-info/WHEEL
chemo_standardizer-0.1.7.dist-info/entry_points.txt
chemo_standardizer-0.1.7.dist-info/top_level.txt
chemo_standardizer-0.1.7.dist-info/RECORD
