Metadata-Version: 2.1
Name: chemo-standardizer
Version: 0.1.7
Summary: Provides a simple way of standardising molecules as a prelude to e.g. molecular modelling exercises.
Home-page: https://www.ebi.ac.uk/chembldb/index.php/ws
Author: Francis Atkinson
Author-email: francis@ebi.ac.uk
License: Apache License, Version 2.0
Platform: UNKNOWN
Classifier: Development Status :: 2 - Pre-Alpha
Classifier: Environment :: Console
Classifier: Intended Audience :: Science/Research
Classifier: License :: OSI Approved :: Apache Software License
Classifier: Operating System :: OS Independent
Classifier: Programming Language :: Python
Classifier: Topic :: Scientific/Engineering :: Chemistry
